NewsSentiment/DatasetPreparer.py
NewsSentiment/SentimentClasses.py
NewsSentiment/__init__.py
NewsSentiment/__main__.py
NewsSentiment/combinations_default.py
NewsSentiment/consts.py
NewsSentiment/controller.py
NewsSentiment/converter_huggingface.py
NewsSentiment/createoverview.py
NewsSentiment/customexceptions.py
NewsSentiment/dataset.py
NewsSentiment/diskdict.py
NewsSentiment/download.py
NewsSentiment/earlystopping.py
NewsSentiment/evaluator.py
NewsSentiment/fxlogger.py
NewsSentiment/infer.py
NewsSentiment/inferrest.py
NewsSentiment/plotter_utils.py
NewsSentiment/train.py
NewsSentiment/knowledge/__init__.py
NewsSentiment/knowledge/knowledgeutils.py
NewsSentiment/knowledge/bingliuopinion/bingliuopinion.py
NewsSentiment/knowledge/bingliuopinion/converter.py
NewsSentiment/knowledge/bingliuopinion/license.txt
NewsSentiment/knowledge/bingliuopinion/negative-words.txt
NewsSentiment/knowledge/bingliuopinion/opinion_polarity.ddict
NewsSentiment/knowledge/bingliuopinion/positive-words.txt
NewsSentiment/knowledge/liwc/dic.py
NewsSentiment/knowledge/liwc/liwc.py
NewsSentiment/knowledge/liwc/liwchelper.py
NewsSentiment/knowledge/liwc/trie.py
NewsSentiment/knowledge/liwc/data/readme.txt
NewsSentiment/knowledge/mpqasubjectivity/converter.py
NewsSentiment/knowledge/mpqasubjectivity/mpqasubjectivity.py
NewsSentiment/knowledge/mpqasubjectivity/subjclueslen1-HLTEMNLP05.tff
NewsSentiment/knowledge/mpqasubjectivity/subjclueslen1-HLTEMNLP05.tff.ddict
NewsSentiment/knowledge/nrcemolex/NRC-Emotion-Lexicon-Wordlevel-v0.92.txt
NewsSentiment/knowledge/nrcemolex/NRC-Emotion-Lexicon-Wordlevel-v0.92.txt.ddict
NewsSentiment/knowledge/nrcemolex/converter.py
NewsSentiment/knowledge/nrcemolex/nrcemolex.py
NewsSentiment/knowledge/zeros/zerosknowledge.py
NewsSentiment/layers/AggregatorForBert.py
NewsSentiment/layers/__init__.py
NewsSentiment/layers/attention.py
NewsSentiment/layers/dynamic_rnn.py
NewsSentiment/layers/point_wise_feed_forward.py
NewsSentiment/layers/pytorchnlpattention.py
NewsSentiment-1.2.28.dist-info/LICENSE
NewsSentiment-1.2.28.dist-info/METADATA
NewsSentiment-1.2.28.dist-info/WHEEL
NewsSentiment-1.2.28.dist-info/top_level.txt
NewsSentiment-1.2.28.dist-info/RECORD
